MANIFEST.in
README.rst
VERSION
requirements.txt
setup.py
kafkaloghandler/__init__.py
kafkaloghandler/kafkaloghandler.py
kafkaloghandler.egg-info/PKG-INFO
kafkaloghandler.egg-info/SOURCES.txt
kafkaloghandler.egg-info/dependency_links.txt
kafkaloghandler.egg-info/requires.txt
kafkaloghandler.egg-info/top_level.txt