Metadata-Version: 1.1
Name: kafkaloghandler
Version: 0.8.0
Summary: Kafka Logging Handler
Home-page: https://gerrit.opencord.org/gitweb?p=kafkaloghandler.git
Author: Zack Williams
Author-email: zdw@opennetworking.org
License: Apache v2
Keywords: kafka,logging,log handler,message bus
Platform: UNKNOWN
Classifier: Development Status :: 4 - Beta
Classifier: Topic :: System :: Logging
Classifier: Topic :: Internet :: Log Analysis
Classifier: License :: OSI Approved :: Apache Software License
Classifier: Programming Language :: Python :: 2.7
Classifier: Programming Language :: Python :: 3
